OrbitVisualization/OrbitVisualization.py
OrbitVisualization/__init__.py
orbitvisualization-1.0.1.dist-info/licenses/LICENSE
orbitvisualization-1.0.1.dist-info/METADATA
orbitvisualization-1.0.1.dist-info/WHEEL
orbitvisualization-1.0.1.dist-info/top_level.txt
orbitvisualization-1.0.1.dist-info/RECORD
