Metadata-Version: 2.4
Name: OrbitVisualization
Version: 1.0.1
License-File: LICENSE
Requires-Dist: numpy
Requires-Dist: matplotlib
Dynamic: license-file
